[
    {
        "href":"https:\/\/divar.ir\/v\/%D9%88%DB%8C%D9%88%D9%84%D9%88%D9%86-%D9%85%D8%AF%D9%84-tf142\/Aa0fZB9m",
        "title":"ویولون مدل tf142",
        "bottom_red_text":null,
        "subtitle":"۲ روز پیش در یزد، خ ۱ دهه فجر",
        "وضعیت":"در حد نو",
        "مایل به معاوضه":"نیستم",
        "قیمت":"۱۳،۰۰۰،۰۰۰ تومان (مقطوع)",
        "توضیحات":"دوستان ویالون در حد نو هست کلا دوماه استفاده نشده آرشه عوض شده بالشتک و کتاب ویالون و کلیفون هم همراهش هست"
    },
    {
        "href":"https:\/\/divar.ir\/v\/%D9%88%DB%8C%D9%88%D9%84%D9%88%D9%86-%DB%B3-%DB%B4-%DA%A9%D8%A7%D8%B1%DA%A9%D8%B1%D8%AF%D9%87-%D9%85%D8%AF%D9%84tf\/AaoPZcn5",
        "title":"ویولون ۳\/۴ کارکرده مدلtf",
        "bottom_red_text":"نردبان شده",
        "subtitle":"۳ روز پیش در یزد",
        "وضعیت":"کارکرده",
        "مایل به معاوضه":"نیستم",
        "قیمت":"۱۳،۵۰۰،۰۰۰ تومان",
        "توضیحات":"ویولون ۳\/۴ مدل tf کار کرده به همراه کیف ساز"
    },
    {
        "href":"https:\/\/divar.ir\/v\/%D9%81%D8%B1%D9%88%D8%B4-%D9%88%DB%8C%D9%88%D9%84%D9%86-%D9%81%D8%A7%D8%B6%D9%84\/AayX1nG0",
        "title":"فروش ویولن فاضل",
        "bottom_red_text":null,
        "subtitle":"۳ روز پیش در یزد",
        "وضعیت":"در حد نو",
        "مایل به معاوضه":"نیستم",
        "قیمت":"۳۱۰،۰۰۰،۰۰۰ تومان",
        "توضیحات":"ساز خودم هست (از بهترین ساخته های آقای فاضل محمدی) که ۱۰ سال باهاش نواختم و ضبطهای بسیار عالی باهاش گرفتم و از بهترین متریال ساخته شده و کاملا مراقبت شده، کاملا سالم و حرفه ای\nبسیار خوش صدا با رزونانس عالی\nنمونه صدای این ساز هم موجود هست\nبرای تست صدا و بازدید هم در خدمت شما هستیم"
    },
    {
        "href":"https:\/\/divar.ir\/v\/%D9%88%DB%8C%D9%88%D9%84%D9%86-tf-142-%D8%B3%D9%81%D8%A7%D8%B1%D8%B4-%D8%A7%D9%86%DA%AF%D9%84%D8%B3%D8%AA%D8%A7%D9%86\/AaxLvMQ2",
        "title":"ویولن tf 142 سفارش انگلستان",
        "bottom_red_text":null,
        "subtitle":"۴ روز پیش در یزد، خ شهید سامیه زرگر",
        "وضعیت":"نو",
        "مایل به معاوضه":"نیستم",
        "قیمت":"۱۴،۰۰۰،۰۰۰ تومان",
        "توضیحات":"ویولن tf142 سفارش انگلستان\nنو \nبه همراه آرشه و کلیفون و بالشتک و کیف\n تخفیف برای خریدار واقعی \nغیرقابل فروش به دلالها!"
    },
    {
        "href":"https:\/\/divar.ir\/v\/%D9%88%DB%8C%D9%88%D9%84%D9%88%D9%86-tf146\/Aagr6aJI",
        "title":"ویولون tf146",
        "bottom_red_text":"نردبان شده",
        "subtitle":"۱ هفته پیش در یزد",
        "وضعیت":"کارکرده",
        "مایل به معاوضه":"نیستم",
        "قیمت":"۱۸،۰۰۰،۰۰۰ تومان",
        "توضیحات":"ویولون tf146 دست دوم ولی تمیز..."
    },
    {
        "href":"https:\/\/divar.ir\/v\/%D9%88%DB%8C%D9%84%D9%88%D9%86-tf\/AamDlqZO",
        "title":"ویلون tf",
        "bottom_red_text":null,
        "subtitle":"۱ هفته پیش در یزد",
        "وضعیت":"در حد نو",
        "مایل به معاوضه":"نیستم",
        "قیمت":"۱۲،۳۰۰،۰۰۰ تومان",
        "توضیحات":"ویلون برند tf \nدر حد نو \nبه همراه کلیه لوازم و کیف و دو کتاب آموزشی"
    },
    {
        "href":"https:\/\/divar.ir\/v\/%D9%88%DB%8C%D9%84%D9%86-%D8%A2%D9%85%D8%A7%D8%AA%DB%8C-%DB%B1%DB%B0%DB%B0\/Aai3bOb3",
        "title":"ویلن آماتی ۱۰۰",
        "bottom_red_text":null,
        "subtitle":"۲ هفته پیش در یزد",
        "وضعیت":"در حد نو",
        "مایل به معاوضه":"نیستم",
        "قیمت":"۶،۰۰۰،۰۰۰ تومان (مقطوع)",
        "توضیحات":"ویلن آماتی ۱۰۰ در حد نو با لوازم جانبی \nو یک عدد بالشتک تقدیم میشود.\nویلن برای شروع و آموزش عالیه"
    },
    {
        "href":"https:\/\/divar.ir\/v\/%D9%88%DB%8C%D8%A7%D9%84%D9%88%D9%86\/Aagj8wWB",
        "title":"ویالون",
        "bottom_red_text":null,
        "subtitle":"۲ هفته پیش در یزد",
        "وضعیت":"در حد نو",
        "مایل به معاوضه":"نیستم",
        "قیمت":"۱۰،۰۰۰،۰۰۰ تومان (مقطوع)",
        "توضیحات":"ویالون دست ساز شرکتی با چوب فر دار رنگ قهوه‌ای تیره در حد آکبند خوش صدا مناسب شروع یادگیری"
    },
    {
        "href":"https:\/\/divar.ir\/v\/%D9%88%DB%8C%D9%88%D9%84%D9%86-tf\/AagPxtxP",
        "title":"ویولن TF",
        "bottom_red_text":null,
        "subtitle":"۲ هفته پیش در یزد",
        "وضعیت":"در حد نو",
        "مایل به معاوضه":"نیستم",
        "قیمت":"۱۳،۵۰۰،۰۰۰ تومان",
        "توضیحات":"ویولن برند tf در حد نو \nبه همراه کیف مخصوص و دو کتاب اموزشی"
    },
    {
        "href":"https:\/\/divar.ir\/v\/%D8%B3%D8%A7%D8%B2-%D8%AD%D8%B1%D9%81%D9%87-%D8%A7%DB%8C-%D8%AF%D8%B3%D8%AA-%D8%B3%D8%A7%D8%B2\/AaavWzvp",
        "title":"ساز حرفه ای دست ساز",
        "bottom_red_text":null,
        "subtitle":"۳ هفته پیش در یزد",
        "وضعیت":"کارکرده",
        "مایل به معاوضه":"نیستم",
        "قیمت":"۳۵،۰۰۰،۰۰۰ تومان",
        "توضیحات":"این ساز دست ساز بوده و تازه ریگلاژ شده و آماده استفاده هست\nصدای بلند و خوبی داره \nبه مشتری واقعی هم تخفیف میدم\nکیف ساز معمولی و آرشه و کلیفون هم داره"
    },
    {
        "href":"https:\/\/divar.ir\/v\/%D9%88%DB%8C%D9%88%D9%84%D9%86-%D8%A7%DB%8C%D8%B1%D8%A7%D9%86%DB%8C\/AaSbuGKX",
        "title":"ویولن ایرانی",
        "bottom_red_text":null,
        "subtitle":"۳ هفته پیش در یزد",
        "وضعیت":"نو",
        "مایل به معاوضه":"نیستم",
        "قیمت":"۴،۸۰۰،۰۰۰ تومان",
        "توضیحات":"ویولن ایرانی"
    }
]